llcat.py
llcat-0.12.0.dist-info/licenses/LICENSE.MIT
llcat-0.12.0.dist-info/METADATA
llcat-0.12.0.dist-info/WHEEL
llcat-0.12.0.dist-info/entry_points.txt
llcat-0.12.0.dist-info/top_level.txt
llcat-0.12.0.dist-info/RECORD
