Metadata-Version: 2.4
Name: llcat
Version: 0.12.0
Summary: /usr/bin/cat for LLMs
Author-email: Chris McKenzie <kristopolous@yahoo.com>
License-Expression: MIT
Project-URL: Homepage, https://github.com/day50-dev/llcat
Project-URL: Bug Tracker, https://github.com/day50-dev/llcat/issues
Keywords: markdown,terminal,renderer,cli,syntax-highlighting
Classifier: Development Status :: 4 - Beta
Classifier: Environment :: Console
Classifier: Intended Audience :: Developers
Classifier: Programming Language :: Python :: 3
Classifier: Programming Language :: Python :: 3.8
Classifier: Programming Language :: Python :: 3.9
Classifier: Programming Language :: Python :: 3.10
Classifier: Programming Language :: Python :: 3.11
Classifier: Topic :: Text Processing :: Markup
Classifier: Topic :: Utilities
Requires-Python: >=3.8
License-File: LICENSE.MIT
Requires-Dist: requests
Dynamic: license-file
